braincog/__init__.py
braincog/utils.py
braincog/base/__init__.py
braincog/base/brainarea/BrainArea.py
braincog/base/brainarea/IPL.py
braincog/base/brainarea/Insula.py
braincog/base/brainarea/PFC.py
braincog/base/brainarea/__init__.py
braincog/base/brainarea/basalganglia.py
braincog/base/brainarea/dACC.py
braincog/base/connection/CustomLinear.py
braincog/base/connection/__init__.py
braincog/base/connection/layer.py
braincog/base/conversion/__init__.py
braincog/base/conversion/convertor.py
braincog/base/conversion/merge.py
braincog/base/conversion/spicalib.py
braincog/base/encoder/__init__.py
braincog/base/encoder/encoder.py
braincog/base/encoder/population_coding.py
braincog/base/encoder/qs_coding.py
braincog/base/learningrule/BCM.py
braincog/base/learningrule/Hebb.py
braincog/base/learningrule/RSTDP.py
braincog/base/learningrule/STDP.py
braincog/base/learningrule/STP.py
braincog/base/learningrule/__init__.py
braincog/base/node/__init__.py
braincog/base/node/node.py
braincog/base/strategy/LateralInhibition.py
braincog/base/strategy/__init__.py
braincog/base/strategy/surrogate.py
braincog/base/utils/__init__.py
braincog/base/utils/criterions.py
braincog/base/utils/visualization.py
braincog/datasets/CUB2002011.py
braincog/datasets/StanfordDogs.py
braincog/datasets/TinyImageNet.py
braincog/datasets/__init__.py
braincog/datasets/cut_mix.py
braincog/datasets/datasets.py
braincog/datasets/gen_input_signal.py
braincog/datasets/rand_aug.py
braincog/datasets/utils.py
braincog/datasets/ESimagenet/ES_imagenet.py
braincog/datasets/ESimagenet/__init__.py
braincog/datasets/ESimagenet/reconstructed_ES_imagenet.py
braincog/datasets/NOmniglot/NOmniglot.py
braincog/datasets/NOmniglot/__init__.py
braincog/datasets/NOmniglot/nomniglot_full.py
braincog/datasets/NOmniglot/nomniglot_nw_ks.py
braincog/datasets/NOmniglot/nomniglot_pair.py
braincog/datasets/NOmniglot/utils.py
braincog/datasets/hmdb_dvs/__init__.py
braincog/datasets/hmdb_dvs/hmdb_dvs.py
braincog-0.2.7.19.dist-info/LICENSE
braincog-0.2.7.19.dist-info/METADATA
braincog-0.2.7.19.dist-info/WHEEL
braincog-0.2.7.19.dist-info/top_level.txt
braincog-0.2.7.19.dist-info/RECORD
