Metadata-Version: 2.1
Name: braincog
Version: 0.2.7.19
Summary: BrainCog is an open source spiking neural network based brain-inspired cognitive intelligence engine for Brain-inspired Artificial Intelligence and brain simulation. More information on braincog can be found on its homepage http://www.brain-cog.network/
Author: braincog
Classifier: Programming Language :: Python :: 3 :: Only
Classifier: Programming Language :: Python :: 3.6
Classifier: Programming Language :: Python :: 3.7
Classifier: Programming Language :: Python :: 3.8
Classifier: Programming Language :: Python :: 3.9
Classifier: License :: Other/Proprietary License
Classifier: Operating System :: OS Independent
Requires-Python: >=3.6
License-File: LICENSE
Requires-Dist: numpy
Requires-Dist: scipy
Requires-Dist: h5py
Requires-Dist: torchvision
Requires-Dist: torchaudio
Requires-Dist: timm
Requires-Dist: scikit-learn
Requires-Dist: einops
Requires-Dist: thop
Requires-Dist: pyyaml
Requires-Dist: matplotlib
Requires-Dist: seaborn
Requires-Dist: pygame
Requires-Dist: dv
Requires-Dist: tensorboard
Requires-Dist: tonic
